wayland/__about__.py
wayland/__init__.py
wayland/__init__.pyi
wayland/__main__.py
wayland/baseobject.py
wayland/constants.py
wayland/debugger.py
wayland/debugger_commands.py
wayland/exceptions.py
wayland/log.py
wayland/message.py
wayland/parser.py
wayland/protocols.json
wayland/proxy.py
wayland/serialiser.py
wayland/singleton.py
wayland/state.py
wayland/typehint.py
wayland/unixsocket.py
wayland/client/__init__.py
wayland/client/debug.py
wayland/client/memory_pool.py
wayland/client/package.py
wayland/client/debug/__init__.py
wayland/client/debug/__main__.py
wayland/client/debug/debugclient.py
wayland/client/debug/debugsocket.py
wayland/client/debug/gui.py
wayland/client/debug/messagelog.py
wayland/client/debug/summarypanel.py
python_wayland-1.0.0.dist-info/METADATA
python_wayland-1.0.0.dist-info/WHEEL
python_wayland-1.0.0.dist-info/licenses/LICENSE
python_wayland-1.0.0.dist-info/RECORD
