Metadata-Version: 2.4
Name: python-wayland
Version: 1.0.0
Summary: An implementation of the Wayland protocol built from the ground up with no runtime dependencies - no libwayland, no C libraries, just Python.
Project-URL: Homepage, https://sr.ht/~gk/python-wayland/
Project-URL: Documentation, https://python-wayland.org
Project-URL: Issues, https://todo.sr.ht/~gk/python-wayland
Project-URL: Source, https://git.sr.ht/~gk/python-wayland
Project-URL: Changelog, https://python-wayland.org/changelog/
Author-email: Graham King <grking.email@gmail.com>
License: MIT License
License-File: LICENSE
Keywords: libwayland,wayland
Classifier: Development Status :: 3 - Alpha
Classifier: Intended Audience :: Developers
Classifier: License :: OSI Approved :: MIT License
Classifier: Programming Language :: Python
Classifier: Programming Language :: Python :: 3.8
Classifier: Programming Language :: Python :: 3.9
Classifier: Programming Language :: Python :: 3.10
Classifier: Programming Language :: Python :: 3.11
Classifier: Programming Language :: Python :: 3.12
Classifier: Programming Language :: Python :: 3.13
Classifier: Programming Language :: Python :: Implementation :: CPython
Requires-Python: >=3.8
Provides-Extra: dev
Requires-Dist: opencv-python; extra == 'dev'
Requires-Dist: textual; extra == 'dev'
